LICENSE
MANIFEST.in
README.md
setup.py
Flask_Stormpath_Plus.egg-info/PKG-INFO
Flask_Stormpath_Plus.egg-info/SOURCES.txt
Flask_Stormpath_Plus.egg-info/dependency_links.txt
Flask_Stormpath_Plus.egg-info/not-zip-safe
Flask_Stormpath_Plus.egg-info/requires.txt
Flask_Stormpath_Plus.egg-info/top_level.txt
flask_stormpath_plus/__init__.py
flask_stormpath_plus/context_processors.py
flask_stormpath_plus/decorators.py
flask_stormpath_plus/errors.py
flask_stormpath_plus/forms.py
flask_stormpath_plus/models.py
flask_stormpath_plus/security.py
flask_stormpath_plus/settings.py
flask_stormpath_plus/views.py
flask_stormpath_plus/templates/flask_stormpath_plus/base.html
flask_stormpath_plus/templates/flask_stormpath_plus/facebook_login_form.html
flask_stormpath_plus/templates/flask_stormpath_plus/forgot.html
flask_stormpath_plus/templates/flask_stormpath_plus/forgot_change.html
flask_stormpath_plus/templates/flask_stormpath_plus/forgot_complete.html
flask_stormpath_plus/templates/flask_stormpath_plus/forgot_email_sent.html
flask_stormpath_plus/templates/flask_stormpath_plus/google_login_form.html
flask_stormpath_plus/templates/flask_stormpath_plus/login.html
flask_stormpath_plus/templates/flask_stormpath_plus/register.html